[
  {
    "id": "6690e62af39c4d6be82908b5",
    "drawNumber": 3990,
    "drawDate": "Thu, 11 Jul 2024",
    "winningNum": [
      "15",
      "17",
      "22",
      "32",
      "34",
      "40"
    ],
    "additionalNum": "6"
  },
  {
    "id": "6690e62af39c4d6be82908bd",
    "drawNumber": 3989,
    "drawDate": "Mon, 08 Jul 2024",
    "winningNum": [
      "15",
      "18",
      "29",
      "34",
      "38",
      "44"
    ],
    "additionalNum": "35"
  },
  {
    "id": "6690e62af39c4d6be82908c5",
    "drawNumber": 3988,
    "drawDate": "Thu, 04 Jul 2024",
    "winningNum": [
      "4",
      "9",
      "12",
      "15",
      "31",
      "44"
    ],
    "additionalNum": "33"
  },
  {
    "id": "6690e62bf39c4d6be82908cd",
    "drawNumber": 3987,
    "drawDate": "Mon, 01 Jul 2024",
    "winningNum": [
      "11",
      "19",
      "21",
      "26",
      "28",
      "33"
    ],
    "additionalNum": "39"
  },
  {
    "id": "6690e62bf39c4d6be82908d5",
    "drawNumber": 3986,
    "drawDate": "Thu, 27 Jun 2024",
    "winningNum": [
      "1",
      "8",
      "11",
      "14",
      "17",
      "30"
    ],
    "additionalNum": "5"
  },
  {
    "id": "6690e62bf39c4d6be82908dd",
    "drawNumber": 3985,
    "drawDate": "Mon, 24 Jun 2024",
    "winningNum": [
      "20",
      "23",
      "28",
      "30",
      "34",
      "49"
    ],
    "additionalNum": "25"
  }
]