[{"id":"683509e8cd896fac289c23b8","drawNumber":4081,"drawDate":"Mon, 26 May 2025","winningNum":["5","9","15","28","46","48"],"additionalNum":"8","winningPool":[{"id":"683509e8cd896fac289c23b9","group":"Group 1","prize":0,"winners":0,"resultId":"683509e8cd896fac289c23b8"},{"id":"683509e8cd896fac289c23ba","group":"Group 2","prize":161611,"winners":4,"resultId":"683509e8cd896fac289c23b8"},{"id":"683509e8cd896fac289c23bb","group":"Group 3","prize":1484,"winners":179,"resultId":"683509e8cd896fac289c23b8"},{"id":"683509e8cd896fac289c23bc","group":"Group 4","prize":234,"winners":621,"resultId":"683509e8cd896fac289c23b8"},{"id":"683509e8cd896fac289c23bd","group":"Group 5","prize":50,"winners":9075,"resultId":"683509e8cd896fac289c23b8"},{"id":"683509e8cd896fac289c23be","group":"Group 6","prize":25,"winners":17993,"resultId":"683509e8cd896fac289c23b8"},{"id":"683509e8cd896fac289c23bf","group":"Group 7","prize":10,"winners":161297,"resultId":"683509e8cd896fac289c23b8"}]},{"id":"683509e9cd896fac289c23c0","drawNumber":4080,"drawDate":"Thu, 22 May 2025","winningNum":["3","10","32","34","44","48"],"additionalNum":"29","winningPool":[{"id":"683509eacd896fac289c23c1","group":"Group 1","prize":0,"winners":0,"resultId":"683509e9cd896fac289c23c0"},{"id":"683509eacd896fac289c23c2","group":"Group 2","prize":0,"winners":0,"resultId":"683509e9cd896fac289c23c0"},{"id":"683509eacd896fac289c23c3","group":"Group 3","prize":1863,"winners":96,"resultId":"683509e9cd896fac289c23c0"},{"id":"683509eacd896fac289c23c4","group":"Group 4","prize":574,"winners":170,"resultId":"683509e9cd896fac289c23c0"},{"id":"683509eacd896fac289c23c5","group":"Group 5","prize":50,"winners":4360,"resultId":"683509e9cd896fac289c23c0"},{"id":"683509eacd896fac289c23c6","group":"Group 6","prize":25,"winners":5909,"resultId":"683509e9cd896fac289c23c0"},{"id":"683509eacd896fac289c23c7","group":"Group 7","prize":10,"winners":85351,"resultId":"683509e9cd896fac289c23c0"}]},{"id":"683509eacd896fac289c23c8","drawNumber":4079,"drawDate":"Mon, 19 May 2025","winningNum":["2","15","17","18","39","45"],"additionalNum":"26","winningPool":[{"id":"683509ebcd896fac289c23c9","group":"Group 1","prize":1279986,"winners":1,"resultId":"683509eacd896fac289c23c8"},{"id":"683509ebcd896fac289c23ca","group":"Group 2","prize":134736,"winners":2,"resultId":"683509eacd896fac289c23c8"},{"id":"683509ebcd896fac289c23cb","group":"Group 3","prize":1971,"winners":94,"resultId":"683509eacd896fac289c23c8"},{"id":"683509ebcd896fac289c23cc","group":"Group 4","prize":410,"winners":247,"resultId":"683509eacd896fac289c23c8"},{"id":"683509ebcd896fac289c23cd","group":"Group 5","prize":50,"winners":4805,"resultId":"683509eacd896fac289c23c8"},{"id":"683509ebcd896fac289c23ce","group":"Group 6","prize":25,"winners":7014,"resultId":"683509eacd896fac289c23c8"},{"id":"683509ebcd896fac289c23cf","group":"Group 7","prize":10,"winners":95577,"resultId":"683509eacd896fac289c23c8"}]},{"id":"683509eccd896fac289c23d0","drawNumber":4078,"drawDate":"Thu, 15 May 2025","winningNum":["9","16","17","20","34","38"],"additionalNum":"18","winningPool":[{"id":"683509eccd896fac289c23d1","group":"Group 1","prize":6029737,"winners":1,"resultId":"683509eccd896fac289c23d0"},{"id":"683509eccd896fac289c23d2","group":"Group 2","prize":202727,"winners":3,"resultId":"683509eccd896fac289c23d0"},{"id":"683509eccd896fac289c23d3","group":"Group 3","prize":2248,"winners":186,"resultId":"683509eccd896fac289c23d0"},{"id":"683509eccd896fac289c23d4","group":"Group 4","prize":415,"winners":550,"resultId":"683509eccd896fac289c23d0"},{"id":"683509eccd896fac289c23d5","group":"Group 5","prize":50,"winners":12073,"resultId":"683509eccd896fac289c23d0"},{"id":"683509eccd896fac289c23d6","group":"Group 6","prize":25,"winners":18150,"resultId":"683509eccd896fac289c23d0"},{"id":"683509eccd896fac289c23d7","group":"Group 7","prize":10,"winners":228643,"resultId":"683509eccd896fac289c23d0"}]},{"id":"683509edcd896fac289c23d8","drawNumber":4077,"drawDate":"Mon, 12 May 2025","winningNum":["6","16","20","23","40","48"],"additionalNum":"45","winningPool":[{"id":"683509edcd896fac289c23d9","group":"Group 1","prize":0,"winners":0,"resultId":"683509edcd896fac289c23d8"},{"id":"683509edcd896fac289c23da","group":"Group 2","prize":65997,"winners":6,"resultId":"683509edcd896fac289c23d8"},{"id":"683509edcd896fac289c23db","group":"Group 3","prize":1973,"winners":138,"resultId":"683509edcd896fac289c23d8"},{"id":"683509edcd896fac289c23dc","group":"Group 4","prize":401,"winners":371,"resultId":"683509edcd896fac289c23d8"},{"id":"683509edcd896fac289c23dd","group":"Group 5","prize":50,"winners":7856,"resultId":"683509edcd896fac289c23d8"},{"id":"683509edcd896fac289c23de","group":"Group 6","prize":25,"winners":9907,"resultId":"683509edcd896fac289c23d8"},{"id":"683509edcd896fac289c23df","group":"Group 7","prize":10,"winners":151903,"resultId":"683509edcd896fac289c23d8"}]},{"id":"683509eecd896fac289c23e0","drawNumber":4076,"drawDate":"Thu, 08 May 2025","winningNum":["9","13","17","39","46","47"],"additionalNum":"22","winningPool":[{"id":"683509eecd896fac289c23e1","group":"Group 1","prize":0,"winners":0,"resultId":"683509eecd896fac289c23e0"},{"id":"683509eecd896fac289c23e2","group":"Group 2","prize":132631,"winners":2,"resultId":"683509eecd896fac289c23e0"},{"id":"683509eecd896fac289c23e3","group":"Group 3","prize":1689,"winners":108,"resultId":"683509eecd896fac289c23e0"},{"id":"683509eecd896fac289c23e4","group":"Group 4","prize":474,"winners":210,"resultId":"683509eecd896fac289c23e0"},{"id":"683509eecd896fac289c23e5","group":"Group 5","prize":50,"winners":4939,"resultId":"683509eecd896fac289c23e0"},{"id":"683509eecd896fac289c23e6","group":"Group 6","prize":25,"winners":6836,"resultId":"683509eecd896fac289c23e0"},{"id":"683509eecd896fac289c23e7","group":"Group 7","prize":10,"winners":94717,"resultId":"683509eecd896fac289c23e0"}]}]