[{"id":"67490464d4da6b4b83ba169e","drawNumber":4030,"drawDate":"Thu, 28 Nov 2024","winningNum":["1","2","4","15","18","24"],"additionalNum":"35","winningPool":[{"id":"67490464d4da6b4b83ba169f","group":"Group 1","prize":0,"winners":0,"resultId":"67490464d4da6b4b83ba169e"},{"id":"67490464d4da6b4b83ba16a0","group":"Group 2","prize":350328,"winners":1,"resultId":"67490464d4da6b4b83ba169e"},{"id":"67490464d4da6b4b83ba16a1","group":"Group 3","prize":923,"winners":261,"resultId":"67490464d4da6b4b83ba169e"},{"id":"67490464d4da6b4b83ba16a2","group":"Group 4","prize":411,"winners":320,"resultId":"67490464d4da6b4b83ba169e"},{"id":"67490464d4da6b4b83ba16a3","group":"Group 5","prize":50,"winners":10837,"resultId":"67490464d4da6b4b83ba169e"},{"id":"67490464d4da6b4b83ba16a4","group":"Group 6","prize":25,"winners":9475,"resultId":"67490464d4da6b4b83ba169e"},{"id":"67490464d4da6b4b83ba16a5","group":"Group 7","prize":10,"winners":172609,"resultId":"67490464d4da6b4b83ba169e"}]},{"id":"67490465d4da6b4b83ba16a6","drawNumber":4029,"drawDate":"Mon, 25 Nov 2024","winningNum":["26","28","31","38","41","42"],"additionalNum":"23","winningPool":[{"id":"67490466d4da6b4b83ba16a7","group":"Group 1","prize":0,"winners":0,"resultId":"67490465d4da6b4b83ba16a6"},{"id":"67490466d4da6b4b83ba16a8","group":"Group 2","prize":130168,"winners":2,"resultId":"67490465d4da6b4b83ba16a6"},{"id":"67490466d4da6b4b83ba16a9","group":"Group 3","prize":2183,"winners":82,"resultId":"67490465d4da6b4b83ba16a6"},{"id":"67490466d4da6b4b83ba16aa","group":"Group 4","prize":442,"winners":221,"resultId":"67490465d4da6b4b83ba16a6"},{"id":"67490466d4da6b4b83ba16ab","group":"Group 5","prize":50,"winners":4628,"resultId":"67490465d4da6b4b83ba16a6"},{"id":"67490466d4da6b4b83ba16ac","group":"Group 6","prize":25,"winners":6799,"resultId":"67490465d4da6b4b83ba16a6"},{"id":"67490466d4da6b4b83ba16ad","group":"Group 7","prize":10,"winners":86865,"resultId":"67490465d4da6b4b83ba16a6"}]},{"id":"67490467d4da6b4b83ba16ae","drawNumber":4028,"drawDate":"Thu, 21 Nov 2024","winningNum":["4","7","11","14","21","28"],"additionalNum":"36","winningPool":[{"id":"67490467d4da6b4b83ba16af","group":"Group 1","prize":91571,"winners":13,"resultId":"67490467d4da6b4b83ba16ae"},{"id":"67490467d4da6b4b83ba16b0","group":"Group 2","prize":41770,"winners":6,"resultId":"67490467d4da6b4b83ba16ae"},{"id":"67490467d4da6b4b83ba16b1","group":"Group 3","prize":405,"winners":426,"resultId":"67490467d4da6b4b83ba16ae"},{"id":"67490467d4da6b4b83ba16b2","group":"Group 4","prize":290,"winners":325,"resultId":"67490467d4da6b4b83ba16ae"},{"id":"67490467d4da6b4b83ba16b3","group":"Group 5","prize":50,"winners":12307,"resultId":"67490467d4da6b4b83ba16ae"},{"id":"67490467d4da6b4b83ba16b4","group":"Group 6","prize":25,"winners":7502,"resultId":"67490467d4da6b4b83ba16ae"},{"id":"67490467d4da6b4b83ba16b5","group":"Group 7","prize":10,"winners":153706,"resultId":"67490467d4da6b4b83ba16ae"}]},{"id":"67490468d4da6b4b83ba16b6","drawNumber":4027,"drawDate":"Mon, 18 Nov 2024","winningNum":["1","2","14","36","44","46"],"additionalNum":"20","winningPool":[{"id":"67490468d4da6b4b83ba16b7","group":"Group 1","prize":616395,"winners":2,"resultId":"67490468d4da6b4b83ba16b6"},{"id":"67490468d4da6b4b83ba16b8","group":"Group 2","prize":86512,"winners":3,"resultId":"67490468d4da6b4b83ba16b6"},{"id":"67490468d4da6b4b83ba16b9","group":"Group 3","prize":1919,"winners":93,"resultId":"67490468d4da6b4b83ba16b6"},{"id":"67490468d4da6b4b83ba16ba","group":"Group 4","prize":408,"winners":239,"resultId":"67490468d4da6b4b83ba16b6"},{"id":"67490468d4da6b4b83ba16bb","group":"Group 5","prize":50,"winners":4313,"resultId":"67490468d4da6b4b83ba16b6"},{"id":"67490468d4da6b4b83ba16bc","group":"Group 6","prize":25,"winners":5872,"resultId":"67490468d4da6b4b83ba16b6"},{"id":"67490468d4da6b4b83ba16bd","group":"Group 7","prize":10,"winners":82317,"resultId":"67490468d4da6b4b83ba16b6"}]},{"id":"67490469d4da6b4b83ba16be","drawNumber":4026,"drawDate":"Thu, 14 Nov 2024","winningNum":["12","16","29","36","39","40"],"additionalNum":"37","winningPool":[{"id":"67490469d4da6b4b83ba16bf","group":"Group 1","prize":3272445,"winners":4,"resultId":"67490469d4da6b4b83ba16be"},{"id":"67490469d4da6b4b83ba16c0","group":"Group 2","prize":114990,"winners":13,"resultId":"67490469d4da6b4b83ba16be"},{"id":"67490469d4da6b4b83ba16c1","group":"Group 3","prize":1791,"winners":574,"resultId":"67490469d4da6b4b83ba16be"},{"id":"67490469d4da6b4b83ba16c2","group":"Group 4","prize":466,"winners":1204,"resultId":"67490469d4da6b4b83ba16be"},{"id":"67490469d4da6b4b83ba16c3","group":"Group 5","prize":50,"winners":29410,"resultId":"67490469d4da6b4b83ba16be"},{"id":"67490469d4da6b4b83ba16c4","group":"Group 6","prize":25,"winners":38930,"resultId":"67490469d4da6b4b83ba16be"},{"id":"67490469d4da6b4b83ba16c5","group":"Group 7","prize":10,"winners":548392,"resultId":"67490469d4da6b4b83ba16be"}]},{"id":"6749046ad4da6b4b83ba16c6","drawNumber":4025,"drawDate":"Mon, 11 Nov 2024","winningNum":["13","28","39","43","46","48"],"additionalNum":"30","winningPool":[{"id":"6749046ad4da6b4b83ba16c7","group":"Group 1","prize":0,"winners":0,"resultId":"6749046ad4da6b4b83ba16c6"},{"id":"6749046ad4da6b4b83ba16c8","group":"Group 2","prize":215010,"winners":3,"resultId":"6749046ad4da6b4b83ba16c6"},{"id":"6749046ad4da6b4b83ba16c9","group":"Group 3","prize":2007,"winners":221,"resultId":"6749046ad4da6b4b83ba16c6"},{"id":"6749046ad4da6b4b83ba16ca","group":"Group 4","prize":418,"winners":579,"resultId":"6749046ad4da6b4b83ba16c6"},{"id":"6749046ad4da6b4b83ba16cb","group":"Group 5","prize":50,"winners":11822,"resultId":"6749046ad4da6b4b83ba16c6"},{"id":"6749046ad4da6b4b83ba16cc","group":"Group 6","prize":25,"winners":16383,"resultId":"6749046ad4da6b4b83ba16c6"},{"id":"6749046ad4da6b4b83ba16cd","group":"Group 7","prize":10,"winners":224035,"resultId":"6749046ad4da6b4b83ba16c6"}]}]