[{"id":"6818097b3e27f2fad77ea4f0","drawNumber":4074,"drawDate":"Thu, 01 May 2025","winningNum":["2","8","12","30","35","49"],"additionalNum":"38","winningPool":[{"id":"6818097b3e27f2fad77ea4f1","group":"Group 1","prize":0,"winners":0,"resultId":"6818097b3e27f2fad77ea4f0"},{"id":"6818097b3e27f2fad77ea4f2","group":"Group 2","prize":128083,"winners":2,"resultId":"6818097b3e27f2fad77ea4f0"},{"id":"6818097b3e27f2fad77ea4f3","group":"Group 3","prize":1616,"winners":109,"resultId":"6818097b3e27f2fad77ea4f0"},{"id":"6818097b3e27f2fad77ea4f4","group":"Group 4","prize":503,"winners":191,"resultId":"6818097b3e27f2fad77ea4f0"},{"id":"6818097b3e27f2fad77ea4f5","group":"Group 5","prize":50,"winners":5713,"resultId":"6818097b3e27f2fad77ea4f0"},{"id":"6818097b3e27f2fad77ea4f6","group":"Group 6","prize":25,"winners":7158,"resultId":"6818097b3e27f2fad77ea4f0"},{"id":"6818097b3e27f2fad77ea4f7","group":"Group 7","prize":10,"winners":109432,"resultId":"6818097b3e27f2fad77ea4f0"}]},{"id":"6818097c3e27f2fad77ea4f8","drawNumber":4073,"drawDate":"Mon, 28 Apr 2025","winningNum":["3","8","12","18","24","41"],"additionalNum":"11","winningPool":[{"id":"6818097c3e27f2fad77ea4f9","group":"Group 1","prize":6464725,"winners":2,"resultId":"6818097c3e27f2fad77ea4f8"},{"id":"6818097c3e27f2fad77ea4fa","group":"Group 2","prize":124689,"winners":12,"resultId":"6818097c3e27f2fad77ea4f8"},{"id":"6818097c3e27f2fad77ea4fb","group":"Group 3","prize":1208,"winners":852,"resultId":"6818097c3e27f2fad77ea4f8"},{"id":"6818097c3e27f2fad77ea4fc","group":"Group 4","prize":241,"winners":2333,"resultId":"6818097c3e27f2fad77ea4f8"},{"id":"6818097c3e27f2fad77ea4fd","group":"Group 5","prize":50,"winners":39650,"resultId":"6818097c3e27f2fad77ea4f8"},{"id":"6818097c3e27f2fad77ea4fe","group":"Group 6","prize":25,"winners":60384,"resultId":"6818097c3e27f2fad77ea4f8"},{"id":"6818097c3e27f2fad77ea4ff","group":"Group 7","prize":10,"winners":666310,"resultId":"6818097c3e27f2fad77ea4f8"}]},{"id":"6818097d3e27f2fad77ea500","drawNumber":4072,"drawDate":"Thu, 24 Apr 2025","winningNum":["17","19","21","23","30","40"],"additionalNum":"33","winningPool":[{"id":"6818097d3e27f2fad77ea501","group":"Group 1","prize":0,"winners":0,"resultId":"6818097d3e27f2fad77ea500"},{"id":"6818097d3e27f2fad77ea502","group":"Group 2","prize":197702,"winners":3,"resultId":"6818097d3e27f2fad77ea500"},{"id":"6818097d3e27f2fad77ea503","group":"Group 3","prize":1516,"winners":269,"resultId":"6818097d3e27f2fad77ea500"},{"id":"6818097d3e27f2fad77ea504","group":"Group 4","prize":432,"winners":515,"resultId":"6818097d3e27f2fad77ea500"},{"id":"6818097d3e27f2fad77ea505","group":"Group 5","prize":50,"winners":13071,"resultId":"6818097d3e27f2fad77ea500"},{"id":"6818097d3e27f2fad77ea506","group":"Group 6","prize":25,"winners":15630,"resultId":"6818097d3e27f2fad77ea500"},{"id":"6818097d3e27f2fad77ea507","group":"Group 7","prize":10,"winners":228993,"resultId":"6818097d3e27f2fad77ea500"}]},{"id":"6818097e3e27f2fad77ea508","drawNumber":4071,"drawDate":"Mon, 21 Apr 2025","winningNum":["1","17","30","37","41","43"],"additionalNum":"32","winningPool":[{"id":"6818097e3e27f2fad77ea509","group":"Group 1","prize":0,"winners":0,"resultId":"6818097e3e27f2fad77ea508"},{"id":"6818097e3e27f2fad77ea50a","group":"Group 2","prize":316308,"winners":2,"resultId":"6818097e3e27f2fad77ea508"},{"id":"6818097e3e27f2fad77ea50b","group":"Group 3","prize":2026,"winners":127,"resultId":"6818097e3e27f2fad77ea508"},{"id":"6818097e3e27f2fad77ea50c","group":"Group 4","prize":503,"winners":279,"resultId":"6818097e3e27f2fad77ea508"},{"id":"6818097e3e27f2fad77ea50d","group":"Group 5","prize":50,"winners":6692,"resultId":"6818097e3e27f2fad77ea508"},{"id":"6818097e3e27f2fad77ea50e","group":"Group 6","prize":25,"winners":8578,"resultId":"6818097e3e27f2fad77ea508"},{"id":"6818097e3e27f2fad77ea50f","group":"Group 7","prize":10,"winners":126457,"resultId":"6818097e3e27f2fad77ea508"}]},{"id":"6818097f3e27f2fad77ea510","drawNumber":4070,"drawDate":"Thu, 17 Apr 2025","winningNum":["15","17","26","31","40","46"],"additionalNum":"19","winningPool":[{"id":"6818097f3e27f2fad77ea511","group":"Group 1","prize":0,"winners":0,"resultId":"6818097f3e27f2fad77ea510"},{"id":"6818097f3e27f2fad77ea512","group":"Group 2","prize":0,"winners":0,"resultId":"6818097f3e27f2fad77ea510"},{"id":"6818097f3e27f2fad77ea513","group":"Group 3","prize":3485,"winners":51,"resultId":"6818097f3e27f2fad77ea510"},{"id":"6818097f3e27f2fad77ea514","group":"Group 4","prize":408,"winners":238,"resultId":"6818097f3e27f2fad77ea510"},{"id":"6818097f3e27f2fad77ea515","group":"Group 5","prize":50,"winners":4624,"resultId":"6818097f3e27f2fad77ea510"},{"id":"6818097f3e27f2fad77ea516","group":"Group 6","prize":25,"winners":6795,"resultId":"6818097f3e27f2fad77ea510"},{"id":"6818097f3e27f2fad77ea517","group":"Group 7","prize":10,"winners":88776,"resultId":"6818097f3e27f2fad77ea510"}]},{"id":"681809803e27f2fad77ea518","drawNumber":4069,"drawDate":"Mon, 14 Apr 2025","winningNum":["6","14","29","30","35","42"],"additionalNum":"25","winningPool":[{"id":"681809803e27f2fad77ea519","group":"Group 1","prize":3072730,"winners":1,"resultId":"681809803e27f2fad77ea518"},{"id":"681809803e27f2fad77ea51a","group":"Group 2","prize":189847,"winners":2,"resultId":"681809803e27f2fad77ea518"},{"id":"681809803e27f2fad77ea51b","group":"Group 3","prize":1741,"winners":150,"resultId":"681809803e27f2fad77ea518"},{"id":"681809803e27f2fad77ea51c","group":"Group 4","prize":441,"winners":323,"resultId":"681809803e27f2fad77ea518"},{"id":"681809803e27f2fad77ea51d","group":"Group 5","prize":50,"winners":7158,"resultId":"681809803e27f2fad77ea518"},{"id":"681809803e27f2fad77ea51e","group":"Group 6","prize":25,"winners":10648,"resultId":"681809803e27f2fad77ea518"},{"id":"681809803e27f2fad77ea51f","group":"Group 7","prize":10,"winners":133852,"resultId":"681809803e27f2fad77ea518"}]}]